XCurve/__init__.py
XCurve/AUPRC/__init__.py
XCurve/AUPRC/configs/__init__.py
XCurve/AUPRC/datasets/__init__.py
XCurve/AUPRC/datasets/base_dataset.py
XCurve/AUPRC/datasets/dataset.py
XCurve/AUPRC/losses/__init__.py
XCurve/AUPRC/losses/base_loss.py
XCurve/AUPRC/losses/loss_warpper.py
XCurve/AUPRC/losses/pair_loss.py
XCurve/AUPRC/losses/soprc.py
XCurve/AUPRC/models/__init__.py
XCurve/AUPRC/models/_resnet.py
XCurve/AUPRC/models/base_model.py
XCurve/AUPRC/models/resnet.py
XCurve/AUPRC/models/retrieval_model.py
XCurve/AUPRC/uni_test/__init__.py
XCurve/AUPRC/uni_test/test_datasets.py
XCurve/AUPRC/uni_test/test_losses.py
XCurve/AUPRC/uni_test/test_metrics.py
XCurve/AUPRC/uni_test/test_models.py
XCurve/AUROC/__init__.py
XCurve/AUROC/dataloaders/__init__.py
XCurve/AUROC/dataloaders/base_dataset.py
XCurve/AUROC/dataloaders/custom_transforms.py
XCurve/AUROC/dataloaders/dataset.py
XCurve/AUROC/dataloaders/imbalance_cifar.py
XCurve/AUROC/dataloaders/mnist_dataset.py
XCurve/AUROC/dataloaders/sampler.py
XCurve/AUROC/dataloaders/utils.py
XCurve/AUROC/losses/PartialAUROC.py
XCurve/AUROC/losses/StandardAUROC.py
XCurve/AUROC/losses/__init__.py
XCurve/AUROC/losses/AdversarialAUROC/AdversarialAUROC.py
XCurve/AUROC/losses/AdversarialAUROC/__init__.py
XCurve/AUROC/losses/AdversarialAUROC/attacker.py
XCurve/AUROC/models/__init__.py
XCurve/AUROC/models/densenet.py
XCurve/AUROC/models/load.py
XCurve/AUROC/models/mlp.py
XCurve/AUROC/models/resnet.py
XCurve/AUROC/models/resnet_s.py
XCurve/AUROC/models/wideresnet.py
XCurve/AUROC/optimizer/ASGDA.py
XCurve/AUROC/optimizer/AdvAUC_opt.py
XCurve/AUROC/optimizer/__init__.py
XCurve/AUROC/optimizer/minmax_opt.py
XCurve/AUTKC/__init__.py
XCurve/AUTKC/dataloaders.py
XCurve/AUTKC/optimizer.py
XCurve/AUTKC/losses/AUTKCLoss.py
XCurve/AUTKC/losses/TopKLoss.py
XCurve/AUTKC/losses/__init__.py
XCurve/AUTKC/utils/__init__.py
XCurve/AUTKC/utils/common_utils.py
XCurve/AUTKC/utils/extract_features_places365.py
XCurve/Metrics/AUROC.py
XCurve/Metrics/AUTKC.py
XCurve-1.1.0.dist-info/METADATA
XCurve-1.1.0.dist-info/WHEEL
XCurve-1.1.0.dist-info/top_level.txt
XCurve-1.1.0.dist-info/RECORD
