Metadata-Version: 2.1
Name: XCurve
Version: 1.1.0
Summary: machine learning package
Home-page: https://github.com/statusrank/XCurve
Author: qqgroup
Author-email: 
Classifier: Programming Language :: Python :: 3.8
Classifier: License :: OSI Approved :: MIT License
Classifier: Operating System :: OS Independent
Requires-Python: >=3.8
Requires-Dist: easydict (>=1.9)
Requires-Dist: imbalanced-learn (>=0.9.1)
Requires-Dist: lmdb (>=1.3.0)
Requires-Dist: numpy (>=1.21.2)
Requires-Dist: opencv-python (>=4.5.5.62)
Requires-Dist: pandas (>=1.1.0)
Requires-Dist: Pillow (>=9.1.1)
Requires-Dist: pytest (>=7.1.2)
Requires-Dist: scikit-learn (>=1.1.1)
Requires-Dist: scipy (>=1.7.1)
Requires-Dist: scikit-image (>=0.18.0)
Requires-Dist: torch (>=1.11.0)
Requires-Dist: torchvision (>=0.12.0)
Requires-Dist: tqdm (>=4.62.2)
